nd_line/__init__.py
nd_line/nd_line.py
nd_line-0.2.0.dist-info/METADATA
nd_line-0.2.0.dist-info/WHEEL
nd_line-0.2.0.dist-info/licenses/LICENSE
nd_line-0.2.0.dist-info/RECORD
