Metadata-Version: 2.1
Name: nd_line
Version: 0.2.0
Summary: Interpolate points on an n-dimensional line by euclidean arc length
Project-URL: Homepage, https://github.com/thedannymarsh/nd_line
Project-URL: Bug Tracker, https://github.com/thedannymarsh/nd_line/issues
Author-email: Daniel Marshall <dpm42@duke.edu>
License-Expression: MIT
License-File: LICENSE
Classifier: License :: OSI Approved :: MIT License
Classifier: Operating System :: OS Independent
Classifier: Programming Language :: Python :: 3
Requires-Python: >=3.7
